visual_auto_gui/__init__.py
visual_auto_gui/untils.py
visual_auto_gui/utils.py
visual_auto_gui-0.1.0.dist-info/METADATA
visual_auto_gui-0.1.0.dist-info/WHEEL
visual_auto_gui-0.1.0.dist-info/top_level.txt
visual_auto_gui-0.1.0.dist-info/RECORD
