Metadata-Version: 2.1
Name: visual-auto-gui
Version: 0.1.0
Summary: automate your pc tasks such as clicking scrolling using python with Visual capability
Home-page: UNKNOWN
Author: Dear Norathee
License: MIT
Platform: UNKNOWN
